mctclient.py
medcattrainer_client-1.2.0.dist-info/METADATA
medcattrainer_client-1.2.0.dist-info/WHEEL
medcattrainer_client-1.2.0.dist-info/top_level.txt
medcattrainer_client-1.2.0.dist-info/RECORD
