Metadata-Version: 2.4
Name: medcattrainer-client
Version: 1.2.0
Summary: Python client for interacting with a MedCATTrainer instance
Author-email: Tom Searle <tom@cogstack.org>
Project-URL: Homepage, https://github.com/CogStack/cogstack-nlp/
Project-URL: Documentation, https://docs.cogstack.org/projects/medcat-trainer
Project-URL: Source, https://github.com/CogStack/cogstack-nlp/
Requires-Python: >=3.10
Requires-Dist: requests
